keros/__init__.py
keros/dataset.py
keros/features.py
keros/filters.py
keros/io.py
keros/model.py
keros/model_tools.py
keros/preprocessing.py
keros-0.1.4.dist-info/LICENSE
keros-0.1.4.dist-info/METADATA
keros-0.1.4.dist-info/WHEEL
keros-0.1.4.dist-info/top_level.txt
keros-0.1.4.dist-info/RECORD
