Metadata-Version: 2.1
Name: keros
Version: 0.1.4
Summary: Pacote destinado ao uso de conceitos de machine learning
Author: Armando Luz Borges
Author-email: armandoari.288@gmail.com
License: MIT License
License-File: LICENSE
Requires-Dist: numpy
Requires-Dist: scikit-learn
Requires-Dist: scikit-image
Requires-Dist: rich
